LICENSE
MANIFEST.in
readme.md
setup.py
realrender/__init__.py
realrender/render.py
realrender.egg-info/PKG-INFO
realrender.egg-info/SOURCES.txt
realrender.egg-info/dependency_links.txt
realrender.egg-info/requires.txt
realrender.egg-info/top_level.txt
realrender/sim3drender/Sim3DR.py
realrender/sim3drender/__init__.py
realrender/sim3drender/_init_paths.py
realrender/sim3drender/lighting.py
realrender/sim3drender/setup.py
realrender/sim3drender/lib/rasterize.cpp
realrender/sim3drender/lib/rasterize.h
realrender/sim3drender/lib/rasterize.pyx
realrender/sim3drender/lib/rasterize_kernel.cpp
realrender/sim3drender/tests/io.cpp
realrender/sim3drender/tests/io.h
realrender/sim3drender/tests/test.cpp