Metadata-Version: 2.1
Name: realrender
Version: 0.0.4
Summary: RealRender: mesh3d render that most reliable.
Home-page: https://github.com/jinfagang/realrender
Author: Lucas Jin
Author-email: 11@qq.com
License: UNKNOWN
Platform: UNKNOWN
Classifier: Programming Language :: Python :: 2
Classifier: Programming Language :: Python :: 3
Classifier: License :: Other/Proprietary License
Classifier: Operating System :: OS Independent
License-File: LICENSE
